{"nome":"Viagem ao Guarujá","sinopse":"Decidimos passar o fim de semana na praia, alugamos uma pousada e fomos para o Guarujá.","autor":"Autor ","participantes":["Yuri","Nicole"],"data":"2024-09-14","exclusivo":false,"capa":"imagem_498396.jpg","partes":[{"nome":"A ida","exclusivo":false,"imagem":"imagem_777041.jpg","descricao":""},{"nome":"A praia","exclusivo":false,"imagem":"imagem_866725.jpg","descricao":""},{"nome":"Caminhada até o aquário ","exclusivo":false,"imagem":"imagem_886026.jpg","descricao":""},{"nome":"O peixe feio","exclusivo":false,"imagem":"imagem_341297.jpeg","descricao":""},{"nome":"Tanque de iguana ","exclusivo":false,"imagem":"imagem_590264.jpg","descricao":""},{"nome":"A iguana","exclusivo":false,"imagem":"imagem_279627.jpg","descricao":""},{"nome":"Os pinguins ","exclusivo":false,"imagem":"imagem_796425.jpg","descricao":""},{"nome":"O jacaré ","exclusivo":false,"imagem":"imagem_541787.jpg","descricao":""},{"nome":"O cagado e os jacarés","exclusivo":false,"imagem":"imagem_286841.jpg","descricao":""},{"nome":"Parada para o pastel ","exclusivo":false,"imagem":"imagem_695280.jpg","descricao":""},{"nome":"Rolê a noite na praia","exclusivo":false,"imagem":"video_188667.mp4","descricao":""},{"nome":"Teste","exclusivo":false,"imagem":"video_807049.mp4","descricao":""}]}